kiva/__init__.py
kiva/client.py
kiva/console.py
kiva/events.py
kiva/exceptions.py
kiva/graph.py
kiva/py.typed
kiva/router.py
kiva/run.py
kiva/state.py
kiva/nodes/__init__.py
kiva/nodes/analyze.py
kiva/nodes/router.py
kiva/nodes/synthesize.py
kiva/workflows/__init__.py
kiva/workflows/executor.py
kiva/workflows/parliament.py
kiva/workflows/router.py
kiva/workflows/supervisor.py
kiva/workflows/utils.py
kiva_sdk-0.5.0.dist-info/METADATA
kiva_sdk-0.5.0.dist-info/WHEEL
kiva_sdk-0.5.0.dist-info/licenses/LICENSE
kiva_sdk-0.5.0.dist-info/RECORD
