Metadata-Version: 2.4
Name: kiva-sdk
Version: 0.5.0
Summary: A multi-agent orchestration SDK for building intelligent workflows
Project-URL: Homepage, https://github.com/Kiva-AI/Kiva-SDK
Project-URL: Documentation, https://github.com/Kiva-AI/Kiva-SDK#readme
Project-URL: Repository, https://github.com/Kiva-AI/Kiva-SDK
Project-URL: Issues, https://github.com/Kiva-AI/Kiva-SDK/issues
Author-email: Xingsandesu <admin@jintongshu.com>
Maintainer-email: Xingsandesu <admin@jintongshu.com>
License: MIT
License-File: LICENSE
Keywords: agents,ai,langchain,langgraph,llm,multi-agent,orchestration,workflow
Classifier: Development Status :: 3 - Alpha
Classifier: Intended Audience :: Developers
Classifier: License :: OSI Approved :: MIT License
Classifier: Operating System :: OS Independent
Classifier: Programming Language :: Python :: 3
Classifier: Programming Language :: Python :: 3.12
Classifier: Topic :: Scientific/Engineering :: Artificial Intelligence
Classifier: Topic :: Software Development :: Libraries :: Python Modules
Classifier: Typing :: Typed
Requires-Python: >=3.12
Requires-Dist: langchain-mcp-adapters>=0.2.1
Requires-Dist: langchain-openai>=1.1.7
Requires-Dist: langchain>=1.2.4
Requires-Dist: langgraph>=1.0.6
Requires-Dist: rich>=14.2.0
